rpk/__init__.py
rpk/rpk.py
rpk-5.4.0.data/data/share/ament_index/resource_index/packages/rpk
rpk-5.4.0.data/data/share/rpk/package.xml
rpk-5.4.0.data/data/share/rpk/tpl/apps/python/{{id}}/CMakeLists.txt.j2
rpk-5.4.0.data/data/share/rpk/tpl/apps/python/{{id}}/LICENSE.j2
rpk-5.4.0.data/data/share/rpk/tpl/apps/python/{{id}}/package.xml.j2
rpk-5.4.0.data/data/share/rpk/tpl/apps/python/{{id}}/launch/{{id}}.launch.py.j2
rpk-5.4.0.data/data/share/rpk/tpl/intents/basic_chatbot/{{id}}/LICENSE.j2
rpk-5.4.0.data/data/share/rpk/tpl/intents/basic_chatbot/{{id}}/README.md.j2
rpk-5.4.0.data/data/share/rpk/tpl/intents/basic_chatbot/{{id}}/package.xml.j2
rpk-5.4.0.data/data/share/rpk/tpl/intents/basic_chatbot/{{id}}/setup.cfg.j2
rpk-5.4.0.data/data/share/rpk/tpl/intents/basic_chatbot/{{id}}/setup.py.j2
rpk-5.4.0.data/data/share/rpk/tpl/intents/basic_chatbot/{{id}}/config/00-defaults.yml.j2
rpk-5.4.0.data/data/share/rpk/tpl/intents/basic_chatbot/{{id}}/config/{{id}}.j2
rpk-5.4.0.data/data/share/rpk/tpl/intents/basic_chatbot/{{id}}/launch/{{id}}.launch.py.j2
rpk-5.4.0.data/data/share/rpk/tpl/intents/basic_chatbot/{{id}}/module/{{id}}.j2
rpk-5.4.0.data/data/share/rpk/tpl/intents/basic_chatbot/{{id}}/module/{{id}}_module.yaml.j2
rpk-5.4.0.data/data/share/rpk/tpl/intents/basic_chatbot/{{id}}/res/{{id}}.j2
rpk-5.4.0.data/data/share/rpk/tpl/intents/basic_chatbot/{{id}}/test/test_copyright.py.j2
rpk-5.4.0.data/data/share/rpk/tpl/intents/basic_chatbot/{{id}}/test/test_flake8.py.j2
rpk-5.4.0.data/data/share/rpk/tpl/intents/basic_chatbot/{{id}}/test/test_pep257.py.j2
rpk-5.4.0.data/data/share/rpk/tpl/intents/basic_chatbot/{{id}}/{{id}}/__init__.py.j2
rpk-5.4.0.data/data/share/rpk/tpl/intents/basic_chatbot/{{id}}/{{id}}/node_impl.py.j2
rpk-5.4.0.data/data/share/rpk/tpl/intents/basic_chatbot/{{id}}/{{id}}/start_node.py.j2
rpk-5.4.0.data/data/share/rpk/tpl/intents/llm_connector_python/{{id}}/LICENSE.j2
rpk-5.4.0.data/data/share/rpk/tpl/intents/llm_connector_python/{{id}}/README.md.j2
rpk-5.4.0.dist-info/licenses/LICENSE
rpk-5.4.0.dist-info/METADATA
rpk-5.4.0.dist-info/WHEEL
rpk-5.4.0.dist-info/entry_points.txt
rpk-5.4.0.dist-info/top_level.txt
rpk-5.4.0.dist-info/zip-safe
rpk-5.4.0.dist-info/RECORD
