Metadata-Version: 2.4
Name: rpk
Version: 5.4.0
Summary: A tool to create and package ROS 2 robot applications
Author: Séverin Lemaignan
Author-email: severin.lemaignan@pal-robotics.com
License: Apache License 2.0
License-File: LICENSE
Requires-Dist: setuptools
Requires-Dist: jinja2
Dynamic: author
Dynamic: author-email
Dynamic: description
Dynamic: license
Dynamic: license-file
Dynamic: requires-dist
Dynamic: summary
